[
  {
    "model": "contact.keytype",
    "pk": 1,
    "fields": {
      "title": "PhoneNumber"
    }
  },
  {
    "model": "contact.keytype",
    "pk": 2,
    "fields": {
      "title": "Email"
    }
  },
  {
    "model": "contact.keytype",
    "pk": 3,
    "fields": {
      "title": "GoogleAccountId"
    }
  },
  {
    "model": "contact.keytype",
    "pk": 4,
    "fields": {
      "title": "BlagodarieKey"
    }
  },

  {
    "model": "contact.symptom",
    "pk": 1,
    "fields": {
      "name": "Нехватка питьевой воды"
    }
  },
  {
    "model": "contact.symptom",
    "pk": 2,
    "fields": {
      "name": "Нехватка еды"
    }
  },
  {
    "model": "contact.symptom",
    "pk": 3,
    "fields": {
      "name": "Нехватка лекарств"
    }
  },
  {
    "model": "contact.symptom",
    "pk": 4,
    "fields": {
      "name": "Слабость"
    }
  },
  {
    "model": "contact.symptom",
    "pk": 5,
    "fields": {
      "name": "Температура"
    }
  },
  {
    "model": "contact.symptom",
    "pk": 6,
    "fields": {
      "name": "Кашель"
    }
  },
  {
    "model": "contact.symptom",
    "pk": 7,
    "fields": {
      "name": "Боль в груди при дыхании"
    }
  },
  {
    "model": "contact.symptom",
    "pk": 8,
    "fields": {
      "name": "Затруднённое дыхание"
    }
  },
  {
    "model": "contact.symptom",
    "pk": 9,
    "fields": {
      "name": "Одышка"
    }
  },
  {
    "model": "contact.symptom",
    "pk": 10,
    "fields": {
      "name": "Сухость носа"
    }
  },
  {
    "model": "contact.symptom",
    "pk": 11,
    "fields": {
      "name": "Головная боль"
    }
  },
  {
    "model": "contact.symptom",
    "pk": 12,
    "fields": {
      "name": "Боль и ломота в мышцах и суставах"
    }
  },
  {
    "model": "contact.symptom",
    "pk": 13,
    "fields": {
      "name": "Рвота"
    }
  },
  {
    "model": "contact.symptom",
    "pk": 14,
    "fields": {
      "name": "Диарея"
    }
  },
  {
    "model": "contact.symptom",
    "pk": 15,
    "fields": {
      "name": "Хорошее самочувствие"
    }
  },
  {
    "model": "contact.symptom",
    "pk": 16,
    "fields": {
      "name": "Сердечная боль"
    }
  },
  {
    "model": "contact.symptom",
    "pk": 17,
    "fields": {
      "name": "Повышенное давление"
    }
  },
  {
    "model": "contact.symptom",
    "pk": 18,
    "fields": {
      "name": "Пониженное давление"
    }
  },
  {
    "model": "contact.symptom",
    "pk": 19,
    "fields": {
      "name": "Хорошее настроение"
    }
  },
  {
    "model": "contact.symptom",
    "pk": 20,
    "fields": {
      "name": "Плохое настроение"
    }
  },
  {
    "model": "contact.symptom",
    "pk": 21,
    "fields": {
      "name": "Зубная боль"
    }
  },
  {
    "model": "contact.symptom",
    "pk": 22,
    "fields": {
      "name": "Боль в ушах"
    }
  },
  {
    "model": "contact.symptom",
    "pk": 23,
    "fields": {
      "name": "Головокружение"
    }
  },
  {
    "model": "contact.symptom",
    "pk": 24,
    "fields": {
      "name": "Аллергия"
    }
  },
  {
    "model": "contact.symptom",
    "pk": 25,
    "fields": {
      "name": "Пробуждение"
    }
  },
  {
    "model": "contact.symptom",
    "pk": 26,
    "fields": {
      "name": "Заложенность носа"
    }
  },
  {
    "model": "contact.symptom",
    "pk": 27,
    "fields": {
      "name": "Насморк"
    }
  },
  {
    "model": "contact.symptom",
    "pk": 28,
    "fields": {
      "name": "Озноб"
    }
  },
  {
    "model": "contact.symptom",
    "pk": 29,
    "fields": {
      "name": "Плохое самочувствие"
    }
  },
  {
    "model": "contact.symptom",
    "pk": 30,
    "fields": {
      "name": "Чувство тревоги"
    }
  },
  {
    "model": "contact.symptom",
    "pk": 31,
    "fields": {
      "name": "Похолодало"
    }
  },
  {
    "model": "contact.symptom",
    "pk": 32,
    "fields": {
      "name": "Потеплело"
    }
  },
  {
    "model": "contact.symptom",
    "pk": 33,
    "fields": {
      "name": "Дождь"
    }
  },
  {
    "model": "contact.symptom",
    "pk": 34,
    "fields": {
      "name": "Ветер"
    }
  },
  {
    "model": "contact.symptom",
    "pk": 35,
    "fields": {
      "name": "Жара"
    }
  },
  {
    "model": "contact.symptom",
    "pk": 36,
    "fields": {
      "name": "Астма"
    }
  },
  {
    "model": "contact.symptom",
    "pk": 37,
    "fields": {
      "name": "Хорошая погода"
    }
  },
  {
    "model": "contact.symptom",
    "pk": 40,
    "fields": {
      "name": "Влажно"
    }
  },
  {
    "model": "contact.symptom",
    "pk": 41,
    "fields": {
      "name": "Сухо"
    }
  },
  {
    "model": "contact.symptom",
    "pk": 42,
    "fields": {
      "name": "Свежо"
    }
  },
  {
    "model": "contact.symptom",
    "pk": 44,
    "fields": {
      "name": "Прием пищи"
    }
  },
  {
    "model": "contact.symptom",
    "pk": 45,
    "fields": {
      "name": "Запор"
    }
  },
  {
    "model": "contact.symptom",
    "pk": 46,
    "fields": {
      "name": "Чихание"
    }
  },
  {
    "model": "contact.symptom",
    "pk": 47,
    "fields": {
      "name": "Першит в горле"
    }
  }
]
